py_holiday_calendar/__init__.py
py_holiday_calendar/py_holiday_calendar.py
py_holiday_calendar-0.0.6.dist-info/LICENSE.txt
py_holiday_calendar-0.0.6.dist-info/METADATA
py_holiday_calendar-0.0.6.dist-info/WHEEL
py_holiday_calendar-0.0.6.dist-info/top_level.txt
py_holiday_calendar-0.0.6.dist-info/RECORD
