Metadata-Version: 2.1
Name: py-holiday-calendar
Version: 0.0.6
Summary: Simple date operations on pandas dataframes of difference and adding business days also adjusted for holidays.
Home-page: https://github.com/Parasgupta44/py_holiday_calendar
Author: Paras Gupta
Author-email: paras.gupta986745@gmail.com
License: MIT
Keywords: sample,business date,development,custom holidays
Platform: UNKNOWN
Classifier: Development Status :: 3 - Alpha
Classifier: Intended Audience :: Developers
Classifier: Natural Language :: English
Classifier: License :: OSI Approved :: MIT License
Classifier: Operating System :: OS Independent
Classifier: Programming Language :: Python
Classifier: Programming Language :: Python :: 3.3
Classifier: Programming Language :: Python :: 3.4
Classifier: Programming Language :: Python :: 3.7
Classifier: Programming Language :: Python :: 3.8
Classifier: Topic :: Software Development :: Libraries :: Python Modules
Requires-Dist: business-calendar
Requires-Dist: pandas
